ogura/__init__.py
ogura/__main__.py
ogura/display.py
ogura/ogura.json
ogura-0.0.6.dist-info/METADATA
ogura-0.0.6.dist-info/WHEEL
ogura-0.0.6.dist-info/entry_points.txt
ogura-0.0.6.dist-info/licenses/LICENSE
ogura-0.0.6.dist-info/RECORD
