Metadata-Version: 2.1
Name: ogura
Version: 0.0.6
Summary: A script that randomly displays one of the Hundred Ogura Poems.
Author-email: Arjun Vishanth <arjunvishanth@gmail.com>
License-File: LICENSE
Classifier: License :: OSI Approved :: MIT License
Classifier: Operating System :: OS Independent
Classifier: Programming Language :: Python :: 3
Requires-Python: >=3.7
